{
  "Countries": [
    {
      "id": 1,
      "name": "India",
      "language": "Hindi",
      "population": 6845321,
      "area": 6541365
    },
    {
      "id": 2,
      "name": "Shrilanka",
      "language": "Hindi",
      "population": 6845321,
      "area": 6541365
    },
    {
      "id": 3,
      "name": "Malaysia",
      "language": "Hindi",
      "population": 6845321,
      "area": 6541365
    },
    {
      "id": 4,
      "name": "Maldives",
      "language": "Hindi",
      "population": 6845321,
      "area": 6541365
    },
    {
      "id": 5,
      "name": "New Zealand",
      "language": "English",
      "population": 6845321,
      "area": 6541365
    },
    {
      "id": 6,
      "name": "Singapore",
      "language": "English",
      "population": 6845321,
      "area": 6541365
    },
    {
      "id": 7,
      "name": "Singapore",
      "language": "English",
      "population": 6845321,
      "area": 6541365
    },
    {
      "id": 8,
      "name": "China",
      "language": "Chinese",
      "population": 6845321,
      "area": 6541365
    },
    {
      "id": 9,
      "name": "Japan",
      "language": "Japanese",
      "population": 6845321,
      "area": 6541365
    },
    {
      "name": ",jhbm",
      "language": "m",
      "population": "mgh",
      "area": "gmg",
      "id": 11
    },
    {
      "name": "aaaaaa",
      "language": "aaaaaaaaaaa",
      "population": "aaaaaaaaa",
      "area": "aaaaaaa",
      "id": 12
    },
    {
      "name": "gn",
      "language": "fgnh",
      "population": "fn",
      "area": "fgn",
      "id": 13
    },
    {
      "name": "pppppp",
      "language": "sssssssss",
      "population": "ppppppppp",
      "area": "sssssssss",
      "id": 15
    }
  ]
}